eegyolk/__init__.py
eegyolk/__main__.py
eegyolk/cli.py
eegyolk/cnt.py
eegyolk/config.py
eegyolk/data_functions.py
eegyolk/display_helper.py
eegyolk/epod_helper.py
eegyolk/epod_models.py
eegyolk/epodium.py
eegyolk/helper_functions.py
eegyolk/initialization_functions.py
eegyolk/loaders.py
eegyolk/ml.py
eegyolk/nn.py
eegyolk/patches.py
eegyolk/processing_fp.py
eegyolk/rawf.py
eegyolk/sequences.py
eegyolk-0.0.10.dist-info/METADATA
eegyolk-0.0.10.dist-info/WHEEL
eegyolk-0.0.10.dist-info/top_level.txt
eegyolk-0.0.10.dist-info/RECORD
