Metadata-Version: 2.1
Name: eegyolk
Version: 0.0.10
Summary: A package for analysis of EEG data
Home-page: https://github.com/eegyolk-ai/eegyolk
Author: A team including the NLeSC and Utrecht University
Author-email: c.moore@esciencecenter.nl
License: Apache v2
Platform: UNKNOWN
Requires-Dist: pyxdf
Requires-Dist: mne
Requires-Dist: textdistance
Requires-Dist: pandas
Requires-Dist: scipy
Requires-Dist: matplotlib
Requires-Dist: h5py
Requires-Dist: scikit-learn
Requires-Dist: IPython
Requires-Dist: mne-features (==0.1)
Requires-Dist: numpy
Requires-Dist: tensorflow
Requires-Dist: sklearn-rvm
Provides-Extra: dev
Requires-Dist: pytest ; extra == 'dev'
Requires-Dist: codestyle ; extra == 'dev'
Requires-Dist: isort ; extra == 'dev'
Requires-Dist: wheel ; extra == 'dev'
